protobuf3_to_dict/__init__.py
protobuf3_to_dict/convertor.py
yc_protobuf3_to_dict-0.3.0.dist-info/LICENSE
yc_protobuf3_to_dict-0.3.0.dist-info/METADATA
yc_protobuf3_to_dict-0.3.0.dist-info/WHEEL
yc_protobuf3_to_dict-0.3.0.dist-info/RECORD
