Metadata-Version: 2.1
Name: yc-protobuf3-to-dict
Version: 0.3.0
Summary: A tiny Python library for creating Python dicts from protocol buffers and the reverse.
Home-page: https://github.com/yepcord/protobuf-to-dict
License: Public Domain
Keywords: protobuf,json,dict
Author: Kapor Zhu
Author-email: kapor.zhu@gmail.com
Requires-Python: >=3.9,<4.0
Classifier: Development Status :: 4 - Beta
Classifier: Intended Audience :: Developers
Classifier: License :: Other/Proprietary License
Classifier: License :: Public Domain
Classifier: Operating System :: OS Independent
Classifier: Programming Language :: Python
Classifier: Programming Language :: Python :: 3
Classifier: Programming Language :: Python :: 3.9
Classifier: Programming Language :: Python :: 3.10
Classifier: Programming Language :: Python :: 3.11
Classifier: Topic :: Software Development :: Libraries :: Python Modules
Requires-Dist: protobuf (>=4.24.4,<5.0.0)
Requires-Dist: python-dateutil (>=2.8.2,<3.0.0)
Project-URL: Repository, https://github.com/yepcord/protobuf-to-dict
